{
    "name": "Jane Doe",
    "email": "jane@example.com",
    "password": "mypassword",
    "isNgo": false,
    "address": "123 Main St, Anytown USA",
    "phone": "555-1234",
    "imageURL": "https://example.com/images/jane.jpg"
  },
  {
    "name": "John Smith",
    "email": "john@example.com",
    "password": "mypassword2",
    "isNgo": false,
    "address": "456 Oak Ave, Anytown USA",
    "phone": "555-5678",
    "imageURL": "https://example.com/images/john.jpg"
  },
  {
    "name": "Acme Charity",
    "email": "acme@example.com",
    "password": "mypassword3",
    "isNgo": true,
    "address": "789 Elm St, Anytown USA",
    "phone": "555-9101",
    "imageURL": "https://example.com/images/acme.jpg"
  }
  